msdiff
