Metadata-Version: 1.1
Name: msdiff
Version: 0.1.1
Summary: Command and library to diff Musescore .mcsx files
Home-page: http://cryptonomicon314.bitbucket.org/msdiff/documentation.md.html
Author: Crypto
Author-email: cryptonomicon.314@gmail.com
License: BSD
Keywords: music musescore
Platform: UNKNOWN
Classifier: License :: OSI Approved :: BSD License
